SMfsrc/__init__.py
SMfsrc/fsrc_data.py
smfsrc-1.0.2.dist-info/METADATA
smfsrc-1.0.2.dist-info/WHEEL
smfsrc-1.0.2.dist-info/top_level.txt
smfsrc-1.0.2.dist-info/RECORD
